[{"title":"githubDB rocks","published":"today","rating":"5 stars","_id":"27e2bb59b4464a2394b37dd4f3971f28"},{"title":"githubDB rocks","published":"yesterday","rating":"5 stars","_id":"8a8f770d97184975af65f92327a8014c"},{"title":"githubDB rocks","published":"today","rating":"4 stars","_id":"e17bb868b54f45b5b95218cc195353ef"},{"title":"githubDB rocks","published":"today","rating":"5 stars","_id":"5e6e102c1abd4c69888bcc0a64cfc59d"},{"title":"githubDB rocks","published":"yesterday","rating":"5 stars","_id":"493c9d98951f403ab2aac1f4dcd6087a"},[{"title":"Testing rocks!","published":"today","rating":"4 stars","_id":"b1cdbb3525b84e8c822fc78896d0ca7b"},{"title":"githubDB rocks","published":"yesterday","rating":"5 stars","_id":"42997c62e1714e9f9d88bf3b87901f3b"},{"title":"githubDB rocks","published":"today","rating":"5 stars","_id":"4ca1c1597ddc4020bc41b4418e7a568e"}]]